[
    {
        "username": "depyonimeu",
        "id": 1364746190147887104,
        "menfess": [
            {
                "postid": "1429408930485227528",
                "text": "cardy!\nbunfoxy one tweet au https://t.co/3eqezrki66"
            }
        ]
    },
    {
        "username": "fiore_fortune",
        "id": 1379752371023093761,
        "menfess": [
            {
                "postid": "1429428570988945415",
                "text": "Svtgf!! Au Oneshoot\nOneshot Au \nTw // death\nKetika opera tuhan memberikan alur cerita plot twist yang menyakitkan. https://t.co/dz0hftfS56"
            }
        ]
    },
    {
        "username": "hungrysirens",
        "id": 1176080854210076672,
        "menfess": [
            {
                "postid": "1429614888733847557",
                "text": "svtgf! -MANIPS\n\nkeeping up with the kims!\n(with the cutie jung behind) https://t.co/kwmKK3HCld"
            }
        ]
    },
    {
        "username": "langbuana28",
        "id": 1428546055419826178,
        "menfess": [
            {
                "postid": "1429710887133274113",
                "text": "cardy! drop AU Fairb1 sama B1gcut1e favorit kalian dongg, kangen baca yang tentang mereka, makasih banyakk\ud83e\udd70"
            }
        ]
    },
    {
        "username": "decchaan",
        "id": 609110718,
        "menfess": [
            {
                "postid": "1429723856760156162",
                "text": "cardy! SHIP \ud83d\udef3 permisiiii\ud83e\udd70\ud83e\udd70 https://t.co/TwjHgnZn85"
            }
        ]
    },
    {
        "username": "wonusshie",
        "id": 817905702727319553,
        "menfess": [
            {
                "postid": "1429731180241428483",
                "text": "cardy! i made something\ud83e\udd2a\n\nhttps://t.co/jRBL73zUSd"
            }
        ]
    },
    {
        "username": "everyone_rin",
        "id": 1392532277758808072,
        "menfess": [
            {
                "postid": "1429748428968546315",
                "text": "Svtgf! -ship\n\nAda yg tau ini fairb1 pas lulusan sopa apa kapan ya?\n\nhttps://t.co/pdBF4dXpYl"
            }
        ]
    },
    {
        "username": "kj615530",
        "id": 1330376518049034240,
        "menfess": [
            {
                "postid": "1429758042195771395",
                "text": "yeo \u2022 ja \u2022 chin \u2022 gu\n[ yeoja (saram) chingu ]\n(gg.) when nama grupnya 'pacar' tapi membernya ga ada yg pernah kena skandal pacaran a.k.a udah terlanjur nyaman di zona friendzone\n*pict hanya pemanis cardy! https://t.co/35RT1UzLxN"
            }
        ]
    }
]