[
    {
        "username": "kkumiso",
        "id": 1342505689671856128,
        "menfess": [
            {
                "postid": "1457903287164932106",
                "text": "Cardy! Kangen dokju gak sih? Beberapa hari ini mereka gak up ig atau weverse :'(  https://t.co/Y9GYoKimTJ"
            }
        ]
    },
    {
        "username": "deepresot_",
        "id": 1437630230630318084,
        "menfess": [
            {
                "postid": "1457922979334082563",
                "text": "Cardy! Mungkin ini yang dinamakan rumah? \n\nbooagle prompt https://t.co/KR0WlDrSIh"
            }
        ]
    },
    {
        "username": "moonwooni",
        "id": 1393958318872297475,
        "menfess": [
            {
                "postid": "1457998871582359554",
                "text": "svtgf! MAU JUNRINNNNN\ud83d\ude2d"
            },
            {
                "postid": "1457999033000210432",
                "text": "svtgf! asli ada au boobi(?) apa ya nama kapalnya itu deh pokoknya mau baca keknya gemes mrk berdua avv"
            }
        ]
    },
    {
        "username": "maewooz",
        "id": 1296754694644101120,
        "menfess": [
            {
                "postid": "1458006465810141188",
                "text": "Cardy! j30ngh@.n tuh bf able banget yah alias pacar dan suami able, tbtb ngebayangin kalo kencan gimana hahaha (main character: \ud83d\ude06\u2728k\u00a1m s0jung\u2728\ud83d\ude06)"
            }
        ]
    },
    {
        "username": "inisigendats",
        "id": 1378604151827951617,
        "menfess": [
            {
                "postid": "1458010577507393536",
                "text": "Cardy! SHIP AU\n\nBelum tau kapan di-up nya. Ada yg mau ditag? Rep uname ya frenn https://t.co/5bZCThxzwU"
            }
        ]
    },
    {
        "username": "reminisnce",
        "id": 1399580915643211776,
        "menfess": [
            {
                "postid": "1458012191861452800",
                "text": "Temanya kayak passionate melancholy gitu ga sih vibe sunrise, fallin light\ud83e\udd7a Mana ada glass bead jg\ud83e\udd7a\ud83d\ude2d svtgf! https://t.co/9iQCPMqD5r"
            }
        ]
    },
    {
        "username": "allrounderyerin",
        "id": 1337031421332840450,
        "menfess": [
            {
                "postid": "1458015338726101002",
                "text": "Cardy! Glass Bead~~ hmm hmm https://t.co/Ukx3ZLMNs4"
            }
        ]
    },
    {
        "username": "mhlley",
        "id": 1359738415500075009,
        "menfess": [
            {
                "postid": "1458020331873054720",
                "text": "Cardy! Now playing : glass bead by gfriend https://t.co/UdlUlugcGg"
            }
        ]
    },
    {
        "username": "woahaeee",
        "id": 794368767471955968,
        "menfess": [
            {
                "postid": "1458033657055268879",
                "text": "Cardy! Aku kepikiran ini kayak glass bead sama teori benang merahnya gfriend https://t.co/AE8m04Kid4"
            }
        ]
    },
    {
        "username": "mrscoupss",
        "id": 1370218916274839559,
        "menfess": [
            {
                "postid": "1458036170693173251",
                "text": "cardy! cadry cardy look at this\n\n\ud83d\ude2d\ud83d\ude2d\u2764\ufe0f https://t.co/Kp9czbJTmn"
            }
        ]
    }
]