[
    {
        "username": "rl8ldl",
        "id": 1289883759488032770,
        "menfess": [
            {
                "postid": "1457548994771570691",
                "text": "svtgf! make u dance x side by side. boleh lah ya collab\ud83e\udd32 https://t.co/G5NtnczCgi"
            }
        ]
    },
    {
        "username": "deepresot_",
        "id": 1437630230630318084,
        "menfess": [
            {
                "postid": "1457560501572018178",
                "text": "Cardy! Good Morning for bunfoxy only \ud83e\udd2b\n\n\ud83d\udc30 : \"Ayo katanya mau beli bubur ayam, apa masih ngantuk sih?\"\n\ud83e\udd8a : \"Huum,\" \n\ud83d\udc30 : \"Ya udah lanjut tidur aja,\" \n\n https://t.co/0yHoUVC2PC"
            },
            {
                "postid": "1457670388138266625",
                "text": "Cardy! Siapa yang tiba-tiba naruh dagu ke pundak sekalian gangguin masak, pas baru pulang kerja?? Yap betul bapak kelinci \ud83e\udd1d\ud83c\udffb\n\nAyok aku bikin oleng kalian ke kapal ultku ini \ud83d\ude06\n https://t.co/5UYTEawFzK"
            },
            {
                "postid": "1457718448126111750",
                "text": "Cardy! Ayok gas mutualan, akunku mostly Bunfoxy sama Hamssollie tapi kapal mana aja aku angkut deh. Yuk! Like or rep aja, avaku umji baju merah"
            }
        ]
    },
    {
        "username": "ai_yko",
        "id": 1412370188574420993,
        "menfess": [
            {
                "postid": "1457640758245269504",
                "text": "Cardy! Kalo di Fisika ada angka Istimewa tapi kalo di aku ada kalian yg istimewa:v"
            }
        ]
    },
    {
        "username": "umjihooney",
        "id": 1222524480427216904,
        "menfess": [
            {
                "postid": "1457668714946519041",
                "text": "svtgf! - ship umjihoon onetweet au\n\nyera : kak jion gak seru https://t.co/Qs2OiKuEG3"
            }
        ]
    },
    {
        "username": "LightA_Flame",
        "id": 1307242461111091200,
        "menfess": [
            {
                "postid": "1457698136210685954",
                "text": "Cardy! Minta au bunfoxy dong!!!"
            }
        ]
    },
    {
        "username": "hjisoo_",
        "id": 1388075634358841344,
        "menfess": [
            {
                "postid": "1457702605916884992",
                "text": "cardy! ak mw promosiin au ku lagii, ini baru aja updatee"
            }
        ]
    },
    {
        "username": "wonwoopacarku",
        "id": 1421079887750651904,
        "menfess": [
            {
                "postid": "1457715154272104451",
                "text": "svtgf! ada yang mau mutualan? aku mostly fairbi tapi kapal lain gasss jugaa butuh temen cardy banyak :D like ajaa nanti aku follow"
            }
        ]
    }
]