[
    {
        "username": "rl8ldl",
        "id": 1289883759488032770,
        "menfess": [
            {
                "postid": "1477988575425839111",
                "text": "cw // ship\n\nhaloo cardy! buat yang suka kapal \ud83d\udc38\ud83d\udc30 aku ada oneshot buat nemenin malam kalian nih hehe. tia<3"
            }
        ]
    },
    {
        "username": "haolahope",
        "id": 1468833913384550403,
        "menfess": [
            {
                "postid": "1478002523860615173",
                "text": "Cardy! Aku abis dengerin lagu mixtape nya woozi pas lirik 'shit, this is red too' langsung keingat yujuu masa \ud83d\ude2d\u2764\ufe0f https://t.co/tXe7CgCsYj"
            }
        ]
    },
    {
        "username": "sheyrendipity__",
        "id": 1326125876002476038,
        "menfess": [
            {
                "postid": "1478014013309337601",
                "text": "Cardy! Angelvoice\n(Baca narasinya dulu)\nhttps://t.co/heUmNtEOqz\nhttps://t.co/ZLgiFtoaIn"
            },
            {
                "postid": "1478014393363402761",
                "text": "Cardy! Angelvoice\n(Baca narasinya dulu)\nCardy! Angelvoice\n(Baca narasinya dulu) wan tweet nya aku taro di rep\nhttps://t.co/heUmNtEOqz"
            }
        ]
    },
    {
        "username": "lunarosies",
        "id": 1456772996803170304,
        "menfess": [
            {
                "postid": "1478023396780920833",
                "text": "guys, saranin wp svtgf! yg worth to read dong. self promotion juga boleh hehe. kalo bisa cast nya bunfoxy/gaetukki ya, atau lainnya juga boleh. TIA \u2661"
            }
        ]
    },
    {
        "username": "k6cil",
        "id": 1465675460507889672,
        "menfess": [
            {
                "postid": "1478189763991674886",
                "text": "svtgf! kwan lagi jarang main sama 98z jadi dia minta alamat mereka satu satu katanya mau dia kirimin jeruk mandarin, trus digodain sama umji \"lu malaikat ya\" HAHAHA uri sebeunchin \ud83e\udd7a https://t.co/v3AjFKBeFC"
            }
        ]
    }
]